Workbook

Sheet Start here
B2: FREE TOOL · 2026
B3: Stock, Sales & Production
B4: For any small business that makes or sells products. Free tool by Houssem Gabsi.
B6: What it does
B7: One place for your products, your sales and the work in progress. It tells you what to make or reorder, what sells, what is late, and what each product really costs you, including your time.
B9: Who it is for
B10: Makers, shops and studios: candles, cosmetics, ceramics, clothing, food, prints, jewelry, furniture, or anything you buy and resell.
B12: Start in 10 minutes
B13: 1 Settings: your currency, what one hour of your work is worth, your sales channels and your work steps.
B14: 2 Products: one row per product. Cost per unit (materials, or what you pay to buy it), making time (0 if you resell), price, stock today, and when to restock.
B15: 3 Sales: one row per sale. Pick the product from the list, type the quantity. Leave the price empty to use the list price.
B16: 4 Production: one row per batch or custom order. Move the step as you go. At "Done", the units are added to your stock.
... B28: unfollow.designs@gmail.com · Houssem Gabsi, Tunis, working worldwide

Sheet Dashboard
B2: DASHBOARD
B3: This week
B4: Everything here updates by itself. Read it every Monday.
B5: ="Period "&TEXT(Settings!C10,"dd mmm")&" – "&TEXT(Settings!C11,"dd mmm yyyy")&" · "&Settings!C7 -> Period 16 Sep – 16 Oct 2026 · TND
B7: Revenue in period | E7: Units sold in period | H7: Average margin
B8: =SUMIFS(Sales!$I$7:$I$504,Sales!$B$7:$B$504,">="&Settings!$C$10,Sales!$B$7:$B$504,"<="&Settings!$C$11) -> 969 | E8: =SUM(Products!$O$7:$O$104) -> 24 | H8: =IFERROR(AVERAGE(Products!$K$7:$K$104),0) -> 0.69614124
B10: Products to restock | E10: Late jobs | H10: Stock value (at cost)
B11: =COUNTIF(Products!$Q$7:$Q$104,"Restock")+COUNTIF(Products!$Q$7:$Q$104,"Out of stock") -> 2 | E11: =COUNTIF(Production!$K$7:$K$204,"Late") -> 1 | H11: =SUM(Products!$R$7:$R$104) -> 930
B13: Best seller | E13: This week, do this | K13: Channel | L13: Revenue (period)
B14: =IF(MAX(Products!$O$7:$O$104)=0,"–",INDEX(Products!$C$7:$C$104,MATCH(MAX(Products!$O$7:$O$104),Products!$O$7:$O$104,0))) -> Fig candle | E14: =IF(B11>0,"→ Restock "&B11&" product(s). Products tab, filter Status.","✓ Stock is fine") -> → Restock 2 product(s). Products tab, filter Status. | K14: =Settings!$G$7 -> Instagram | L14: =IF(K14="","",SUMIFS(Sales!$I$7:$I$504,Sales!$F$7:$F$504,K14,Sales!$B$7:$B$504,">="&Settings!$C$10,Sales!$B$7:$B$504,"<="&Settings!$C$11)) -> 292
E15: =IF(E11>0,"→ "&E11&" late job(s). Check Production.","✓ No late jobs") -> → 1 late job(s). Check Production. | K15: =Settings!$G$8 -> Website | L15: =IF(K15="","",SUMIFS(Sales!$I$7:$I$504,Sales!$F$7:$F$504,K15,Sales!$B$7:$B$504,">="&Settings!$C$10,Sales!$B$7:$B$504,"<="&Settings!$C$11)) -> 260
E16: =IF(COUNTIF(Production!$K$7:$K$204,"Due soon")>0,"→ "&COUNTIF(Production!$K$7:$K$204,"Due soon")&" job(s) due soon.","✓ Nothing due soon") -> → 1 job(s) due soon. | K16: =Settings!$G$9 -> Marketplace | L16: =IF(K16="","",SUMIFS(Sales!$I$7:$I$504,Sales!$F$7:$F$504,K16,Sales!$B$7:$B$504,">="&Settings!$C$10,Sales!$B$7:$B$504,"<="&Settings!$C$11)) -> 90
E17: =IF(B14="–","No sales yet in this period","→ "&B14&" sells best. Enough in stock?") -> → Fig candle sells best. Enough in stock? | K17: =Settings!$G$10 -> Shop / in person | L17: =IF(K17="","",SUMIFS(Sales!$I$7:$I$504,Sales!$F$7:$F$504,K17,Sales!$B$7:$B$504,">="&Settings!$C$10,Sales!$B$7:$B$504,"<="&Settings!$C$11)) -> 169
K18: =Settings!$G$11 -> WhatsApp | L18: =IF(K18="","",SUMIFS(Sales!$I$7:$I$504,Sales!$F$7:$F$504,K18,Sales!$B$7:$B$504,">="&Settings!$C$10,Sales!$B$7:$B$504,"<="&Settings!$C$11)) -> 38
B19: Revenue, last 8 weeks | K19: =Settings!$G$12 -> Wholesale | L19: =IF(K19="","",SUMIFS(Sales!$I$7:$I$504,Sales!$F$7:$F$504,K19,Sales!$B$7:$B$504,">="&Settings!$C$10,Sales!$B$7:$B$504,"<="&Settings!$C$11)) -> 120
B34: Free tool by Houssem Gabsi · Want it connected to your shop so it updates itself? unfollow.designs@gmail.com
K38: Chart data (updates itself)
K39: Week of | L39: Revenue
K40: =TEXT(Settings!$C$9-7*7-6,"dd mmm") -> 22 Aug | L40: =SUMIFS(Sales!$I$7:$I$504,Sales!$B$7:$B$504,">="&(Settings!$C$9-7*7-6),Sales!$B$7:$B$504,"<="&(Settings!$C$9-7*7)) -> 98
K41: =TEXT(Settings!$C$9-7*6-6,"dd mmm") -> 29 Aug | L41: =SUMIFS(Sales!$I$7:$I$504,Sales!$B$7:$B$504,">="&(Settings!$C$9-7*6-6),Sales!$B$7:$B$504,"<="&(Settings!$C$9-7*6)) -> 145
K42: =TEXT(Settings!$C$9-7*5-6,"dd mmm") -> 05 Sep | L42: =SUMIFS(Sales!$I$7:$I$504,Sales!$B$7:$B$504,">="&(Settings!$C$9-7*5-6),Sales!$B$7:$B$504,"<="&(Settings!$C$9-7*5)) -> 211
K43: =TEXT(Settings!$C$9-7*4-6,"dd mmm") -> 12 Sep | L43: =SUMIFS(Sales!$I$7:$I$504,Sales!$B$7:$B$504,">="&(Settings!$C$9-7*4-6),Sales!$B$7:$B$504,"<="&(Settings!$C$9-7*4)) -> 196
K44: =TEXT(Settings!$C$9-7*3-6,"dd mmm") -> 19 Sep | L44: =SUMIFS(Sales!$I$7:$I$504,Sales!$B$7:$B$504,">="&(Settings!$C$9-7*3-6),Sales!$B$7:$B$504,"<="&(Settings!$C$9-7*3)) -> 155
K45: =TEXT(Settings!$C$9-7*2-6,"dd mmm") -> 26 Sep | L45: =SUMIFS(Sales!$I$7:$I$504,Sales!$B$7:$B$504,">="&(Settings!$C$9-7*2-6),Sales!$B$7:$B$504,"<="&(Settings!$C$9-7*2)) -> 174
K46: =TEXT(Settings!$C$9-7*1-6,"dd mmm") -> 03 Oct | L46: =SUMIFS(Sales!$I$7:$I$504,Sales!$B$7:$B$504,">="&(Settings!$C$9-7*1-6),Sales!$B$7:$B$504,"<="&(Settings!$C$9-7*1)) -> 223
K47: =TEXT(Settings!$C$9-7*0-6,"dd mmm") -> 10 Oct | L47: =SUMIFS(Sales!$I$7:$I$504,Sales!$B$7:$B$504,">="&(Settings!$C$9-7*0-6),Sales!$B$7:$B$504,"<="&(Settings!$C$9-7*0)) -> 341

Sheet Settings
B2: SETUP
B3: Settings
B4: Your numbers and your lists.
E6: Work steps | G6: Sales channels
B7: Currency (label) | C7: TND | E7: To do | G7: Instagram
B8: One hour of your work is worth | C8: 15 | E8: Making | G8: Website
B9: Today's date | C9: =TODAY() -> 46311 | E9: Finishing | G9: Marketplace
B10: Period start | C10: =C9-30 -> 46281 | E10: Quality check | G10: Shop / in person
B11: Period end | C11: =C9 -> 46311 | E11: Packing | G11: WhatsApp
B12: "Due soon" warning (days) | C12: 3 | E12: Done | G12: Wholesale
B13: Change the period to look at any month. Default: last 30 days.
E14: Keep "Done" last.

Sheet Products
B2: STOCK
B3: Products
B4: One row per product. Warm cells are yours, the rest calculates itself.
B6: SKU | C6: Product | D6: Category | E6: Cost per unit | F6: Making time (min) | G6: Price | H6: Stock at start | I6: Restock at | J6: Real cost per unit | K6: Margin | L6: Made (jobs done) | M6: Sold (all time) | N6: In stock | O6: Sold in period | P6: Days of stock left | Q6: Status | R6: Stock value
B7: CND-01 | C7: Fig candle | D7: Candles | E7: 6 | F7: 20 | G7: 38 | H7: 14 | I7: 8 | J7: =IF(B7="","",E7+F7/60*Settings!$C$8) -> 11 | K7: =IF(OR(B7="",G7=0),"",(G7-J7)/G7) -> 0.71052632 | L7: =IF(B7="","",SUMIFS(Production!$E$7:$E$204,Production!$C$7:$C$204,B7,Production!$G$7:$G$204,"Done")) -> 12 | M7: =IF(B7="","",SUMIFS(Sales!$E$7:$E$504,Sales!$C$7:$C$504,B7)) -> 9 | N7: =IF(B7="","",H7+L7-M7) -> 17 | O7: =IF(B7="","",SUMIFS(Sales!$E$7:$E$504,Sales!$C$7:$C$504,B7,Sales!$B$7:$B$504,">="&Settings!$C$10,Sales!$B$7:$B$504,"<="&Settings!$C$11)) -> 6 | P7: =IF(OR(B7="",O7=0),"",MAX(N7,0)/(O7/MAX(1,Settings!$C$11-Settings!$C$10))) -> 85 | Q7: =IF(B7="","",IF(N7<=0,"Out of stock",IF(N7<=I7,"Restock","OK"))) -> OK | R7: =IF(B7="","",MAX(N7,0)*J7) -> 187
B8: CND-02 | C8: Cedar candle | D8: Candles | E8: 6 | F8: 20 | G8: 38 | H8: 10 | I8: 8 | J8: =IF(B8="","",E8+F8/60*Settings!$C$8) -> 11 | K8: =IF(OR(B8="",G8=0),"",(G8-J8)/G8) -> 0.71052632 | L8: =IF(B8="","",SUMIFS(Production!$E$7:$E$204,Production!$C$7:$C$204,B8,Production!$G$7:$G$204,"Done")) -> 0 | M8: =IF(B8="","",SUMIFS(Sales!$E$7:$E$504,Sales!$C$7:$C$504,B8)) -> 9 | N8: =IF(B8="","",H8+L8-M8) -> 1 | O8: =IF(B8="","",SUMIFS(Sales!$E$7:$E$504,Sales!$C$7:$C$504,B8,Sales!$B$7:$B$504,">="&Settings!$C$10,Sales!$B$7:$B$504,"<="&Settings!$C$11)) -> 6 | P8: =IF(OR(B8="",O8=0),"",MAX(N8,0)/(O8/MAX(1,Settings!$C$11-Settings!$C$10))) -> 5 | Q8: =IF(B8="","",IF(N8<=0,"Out of stock",IF(N8<=I8,"Restock","OK"))) -> Restock | R8: =IF(B8="","",MAX(N8,0)*J8) -> 11
B9: CER-01 | C9: Stoneware mug | D9: Ceramics | E9: 9 | F9: 45 | G9: 55 | H9: 10 | I9: 4 | J9: =IF(B9="","",E9+F9/60*Settings!$C$8) -> 20.25 | K9: =IF(OR(B9="",G9=0),"",(G9-J9)/G9) -> 0.63181818 | L9: =IF(B9="","",SUMIFS(Production!$E$7:$E$204,Production!$C$7:$C$204,B9,Production!$G$7:$G$204,"Done")) -> 0 | M9: =IF(B9="","",SUMIFS(Sales!$E$7:$E$504,Sales!$C$7:$C$504,B9)) -> 4 | N9: =IF(B9="","",H9+L9-M9) -> 6 | O9: =IF(B9="","",SUMIFS(Sales!$E$7:$E$504,Sales!$C$7:$C$504,B9,Sales!$B$7:$B$504,">="&Settings!$C$10,Sales!$B$7:$B$504,"<="&Settings!$C$11)) -> 3 | P9: =IF(OR(B9="",O9=0),"",MAX(N9,0)/(O9/MAX(1,Settings!$C$11-Settings!$C$10))) -> 60 | Q9: =IF(B9="","",IF(N9<=0,"Out of stock",IF(N9<=I9,"Restock","OK"))) -> OK | R9: =IF(B9="","",MAX(N9,0)*J9) -> 121.5
B10: CER-02 | C10: Serving bowl | D10: Ceramics | E10: 14 | F10: 70 | G10: 95 | H10: 3 | I10: 2 | J10: =IF(B10="","",E10+F10/60*Settings!$C$8) -> 31.5 | K10: =IF(OR(B10="",G10=0),"",(G10-J10)/G10) -> 0.66842105 | L10: =IF(B10="","",SUMIFS(Production!$E$7:$E$204,Production!$C$7:$C$204,B10,Production!$G$7:$G$204,"Done")) -> 0 | M10: =IF(B10="","",SUMIFS(Sales!$E$7:$E$504,Sales!$C$7:$C$504,B10)) -> 1 | N10: =IF(B10="","",H10+L10-M10) -> 2 | O10: =IF(B10="","",SUMIFS(Sales!$E$7:$E$504,Sales!$C$7:$C$504,B10,Sales!$B$7:$B$504,">="&Settings!$C$10,Sales!$B$7:$B$504,"<="&Settings!$C$11)) -> 1 | P10: =IF(OR(B10="",O10=0),"",MAX(N10,0)/(O10/MAX(1,Settings!$C$11-Settings!$C$10))) -> 60 | Q10: =IF(B10="","",IF(N10<=0,"Out of stock",IF(N10<=I10,"Restock","OK"))) -> Restock | R10: =IF(B10="","",MAX(N10,0)*J10) -> 63
B11: TXT-01 | C11: Linen tote | D11: Textile | E11: 11 | F11: 30 | G11: 45 | H11: 25 | I11: 6 | J11: =IF(B11="","",E11+F11/60*Settings!$C$8) -> 18.5 | K11: =IF(OR(B11="",G11=0),"",(G11-J11)/G11) -> 0.58888889 | L11: =IF(B11="","",SUMIFS(Production!$E$7:$E$204,Production!$C$7:$C$204,B11,Production!$G$7:$G$204,"Done")) -> 0 | M11: =IF(B11="","",SUMIFS(Sales!$E$7:$E$504,Sales!$C$7:$C$504,B11)) -> 6 | N11: =IF(B11="","",H11+L11-M11) -> 19 | O11: =IF(B11="","",SUMIFS(Sales!$E$7:$E$504,Sales!$C$7:$C$504,B11,Sales!$B$7:$B$504,">="&Settings!$C$10,Sales!$B$7:$B$504,"<="&Settings!$C$11)) -> 3 | P11: =IF(OR(B11="",O11=0),"",MAX(N11,0)/(O11/MAX(1,Settings!$C$11-Settings!$C$10))) -> 190 | Q11: =IF(B11="","",IF(N11<=0,"Out of stock",IF(N11<=I11,"Restock","OK"))) -> OK | R11: =IF(B11="","",MAX(N11,0)*J11) -> 351.5
B12: PRN-01 | C12: Art print A3 | D12: Prints | E12: 4 | F12: 0 | G12: 30 | H12: 40 | I12: 10 | J12: =IF(B12="","",E12+F12/60*Settings!$C$8) -> 4 | K12: =IF(OR(B12="",G12=0),"",(G12-J12)/G12) -> 0.86666667 | L12: =IF(B12="","",SUMIFS(Production!$E$7:$E$204,Production!$C$7:$C$204,B12,Production!$G$7:$G$204,"Done")) -> 20 | M12: =IF(B12="","",SUMIFS(Sales!$E$7:$E$504,Sales!$C$7:$C$504,B12)) -> 11 | N12: =IF(B12="","",H12+L12-M12) -> 49 | O12: =IF(B12="","",SUMIFS(Sales!$E$7:$E$504,Sales!$C$7:$C$504,B12,Sales!$B$7:$B$504,">="&Settings!$C$10,Sales!$B$7:$B$504,"<="&Settings!$C$11)) -> 5 | P12: =IF(OR(B12="",O12=0),"",MAX(N12,0)/(O12/MAX(1,Settings!$C$11-Settings!$C$10))) -> 294 | Q12: =IF(B12="","",IF(N12<=0,"Out of stock",IF(N12<=I12,"Restock","OK"))) -> OK | R12: =IF(B12="","",MAX(N12,0)*J12) -> 196
J13: =IF(B13="","",E13+F13/60*Settings!$C$8) | K13: =IF(OR(B13="",G13=0),"",(G13-J13)/G13) | L13: =IF(B13="","",SUMIFS(Production!$E$7:$E$204,Production!$C$7:$C$204,B13,Production!$G$7:$G$204,"Done")) | M13: =IF(B13="","",SUMIFS(Sales!$E$7:$E$504,Sales!$C$7:$C$504,B13)) | N13: =IF(B13="","",H13+L13-M13) | O13: =IF(B13="","",SUMIFS(Sales!$E$7:$E$504,Sales!$C$7:$C$504,B13,Sales!$B$7:$B$504,">="&Settings!$C$10,Sales!$B$7:$B$504,"<="&Settings!$C$11)) | P13: =IF(OR(B13="",O13=0),"",MAX(N13,0)/(O13/MAX(1,Settings!$C$11-Settings!$C$10))) | Q13: =IF(B13="","",IF(N13<=0,"Out of stock",IF(N13<=I13,"Restock","OK"))) | R13: =IF(B13="","",MAX(N13,0)*J13)
J14: =IF(B14="","",E14+F14/60*Settings!$C$8) | K14: =IF(OR(B14="",G14=0),"",(G14-J14)/G14) | L14: =IF(B14="","",SUMIFS(Production!$E$7:$E$204,Production!$C$7:$C$204,B14,Production!$G$7:$G$204,"Done")) | M14: =IF(B14="","",SUMIFS(Sales!$E$7:$E$504,Sales!$C$7:$C$504,B14)) | N14: =IF(B14="","",H14+L14-M14) | O14: =IF(B14="","",SUMIFS(Sales!$E$7:$E$504,Sales!$C$7:$C$504,B14,Sales!$B$7:$B$504,">="&Settings!$C$10,Sales!$B$7:$B$504,"<="&Settings!$C$11)) | P14: =IF(OR(B14="",O14=0),"",MAX(N14,0)/(O14/MAX(1,Settings!$C$11-Settings!$C$10))) | Q14: =IF(B14="","",IF(N14<=0,"Out of stock",IF(N14<=I14,"Restock","OK"))) | R14: =IF(B14="","",MAX(N14,0)*J14)
J15: =IF(B15="","",E15+F15/60*Settings!$C$8) | K15: =IF(OR(B15="",G15=0),"",(G15-J15)/G15) | L15: =IF(B15="","",SUMIFS(Production!$E$7:$E$204,Production!$C$7:$C$204,B15,Production!$G$7:$G$204,"Done")) | M15: =IF(B15="","",SUMIFS(Sales!$E$7:$E$504,Sales!$C$7:$C$504,B15)) | N15: =IF(B15="","",H15+L15-M15) | O15: =IF(B15="","",SUMIFS(Sales!$E$7:$E$504,Sales!$C$7:$C$504,B15,Sales!$B$7:$B$504,">="&Settings!$C$10,Sales!$B$7:$B$504,"<="&Settings!$C$11)) | P15: =IF(OR(B15="",O15=0),"",MAX(N15,0)/(O15/MAX(1,Settings!$C$11-Settings!$C$10))) | Q15: =IF(B15="","",IF(N15<=0,"Out of stock",IF(N15<=I15,"Restock","OK"))) | R15: =IF(B15="","",MAX(N15,0)*J15)
J16: =IF(B16="","",E16+F16/60*Settings!$C$8) | K16: =IF(OR(B16="",G16=0),"",(G16-J16)/G16) | L16: =IF(B16="","",SUMIFS(Production!$E$7:$E$204,Production!$C$7:$C$204,B16,Production!$G$7:$G$204,"Done")) | M16: =IF(B16="","",SUMIFS(Sales!$E$7:$E$504,Sales!$C$7:$C$504,B16)) | N16: =IF(B16="","",H16+L16-M16) | O16: =IF(B16="","",SUMIFS(Sales!$E$7:$E$504,Sales!$C$7:$C$504,B16,Sales!$B$7:$B$504,">="&Settings!$C$10,Sales!$B$7:$B$504,"<="&Settings!$C$11)) | P16: =IF(OR(B16="",O16=0),"",MAX(N16,0)/(O16/MAX(1,Settings!$C$11-Settings!$C$10))) | Q16: =IF(B16="","",IF(N16<=0,"Out of stock",IF(N16<=I16,"Restock","OK"))) | R16: =IF(B16="","",MAX(N16,0)*J16)
J17: =IF(B17="","",E17+F17/60*Settings!$C$8) | K17: =IF(OR(B17="",G17=0),"",(G17-J17)/G17) | L17: =IF(B17="","",SUMIFS(Production!$E$7:$E$204,Production!$C$7:$C$204,B17,Production!$G$7:$G$204,"Done")) | M17: =IF(B17="","",SUMIFS(Sales!$E$7:$E$504,Sales!$C$7:$C$504,B17)) | N17: =IF(B17="","",H17+L17-M17) | O17: =IF(B17="","",SUMIFS(Sales!$E$7:$E$504,Sales!$C$7:$C$504,B17,Sales!$B$7:$B$504,">="&Settings!$C$10,Sales!$B$7:$B$504,"<="&Settings!$C$11)) | P17: =IF(OR(B17="",O17=0),"",MAX(N17,0)/(O17/MAX(1,Settings!$C$11-Settings!$C$10))) | Q17: =IF(B17="","",IF(N17<=0,"Out of stock",IF(N17<=I17,"Restock","OK"))) | R17: =IF(B17="","",MAX(N17,0)*J17)
J18: =IF(B18="","",E18+F18/60*Settings!$C$8) | K18: =IF(OR(B18="",G18=0),"",(G18-J18)/G18) | L18: =IF(B18="","",SUMIFS(Production!$E$7:$E$204,Production!$C$7:$C$204,B18,Production!$G$7:$G$204,"Done")) | M18: =IF(B18="","",SUMIFS(Sales!$E$7:$E$504,Sales!$C$7:$C$504,B18)) | N18: =IF(B18="","",H18+L18-M18) | O18: =IF(B18="","",SUMIFS(Sales!$E$7:$E$504,Sales!$C$7:$C$504,B18,Sales!$B$7:$B$504,">="&Settings!$C$10,Sales!$B$7:$B$504,"<="&Settings!$C$11)) | P18: =IF(OR(B18="",O18=0),"",MAX(N18,0)/(O18/MAX(1,Settings!$C$11-Settings!$C$10))) | Q18: =IF(B18="","",IF(N18<=0,"Out of stock",IF(N18<=I18,"Restock","OK"))) | R18: =IF(B18="","",MAX(N18,0)*J18)
J19: =IF(B19="","",E19+F19/60*Settings!$C$8) | K19: =IF(OR(B19="",G19=0),"",(G19-J19)/G19) | L19: =IF(B19="","",SUMIFS(Production!$E$7:$E$204,Production!$C$7:$C$204,B19,Production!$G$7:$G$204,"Done")) | M19: =IF(B19="","",SUMIFS(Sales!$E$7:$E$504,Sales!$C$7:$C$504,B19)) | N19: =IF(B19="","",H19+L19-M19) | O19: =IF(B19="","",SUMIFS(Sales!$E$7:$E$504,Sales!$C$7:$C$504,B19,Sales!$B$7:$B$504,">="&Settings!$C$10,Sales!$B$7:$B$504,"<="&Settings!$C$11)) | P19: =IF(OR(B19="",O19=0),"",MAX(N19,0)/(O19/MAX(1,Settings!$C$11-Settings!$C$10))) | Q19: =IF(B19="","",IF(N19<=0,"Out of stock",IF(N19<=I19,"Restock","OK"))) | R19: =IF(B19="","",MAX(N19,0)*J19)
J20: =IF(B20="","",E20+F20/60*Settings!$C$8) | K20: =IF(OR(B20="",G20=0),"",(G20-J20)/G20) | L20: =IF(B20="","",SUMIFS(Production!$E$7:$E$204,Production!$C$7:$C$204,B20,Production!$G$7:$G$204,"Done")) | M20: =IF(B20="","",SUMIFS(Sales!$E$7:$E$504,Sales!$C$7:$C$504,B20)) | N20: =IF(B20="","",H20+L20-M20) | O20: =IF(B20="","",SUMIFS(Sales!$E$7:$E$504,Sales!$C$7:$C$504,B20,Sales!$B$7:$B$504,">="&Settings!$C$10,Sales!$B$7:$B$504,"<="&Settings!$C$11)) | P20: =IF(OR(B20="",O20=0),"",MAX(N20,0)/(O20/MAX(1,Settings!$C$11-Settings!$C$10))) | Q20: =IF(B20="","",IF(N20<=0,"Out of stock",IF(N20<=I20,"Restock","OK"))) | R20: =IF(B20="","",MAX(N20,0)*J20)
J21: =IF(B21="","",E21+F21/60*Settings!$C$8) | K21: =IF(OR(B21="",G21=0),"",(G21-J21)/G21) | L21: =IF(B21="","",SUMIFS(Production!$E$7:$E$204,Production!$C$7:$C$204,B21,Production!$G$7:$G$204,"Done")) | M21: =IF(B21="","",SUMIFS(Sales!$E$7:$E$504,Sales!$C$7:$C$504,B21)) | N21: =IF(B21="","",H21+L21-M21) | O21: =IF(B21="","",SUMIFS(Sales!$E$7:$E$504,Sales!$C$7:$C$504,B21,Sales!$B$7:$B$504,">="&Settings!$C$10,Sales!$B$7:$B$504,"<="&Settings!$C$11)) | P21: =IF(OR(B21="",O21=0),"",MAX(N21,0)/(O21/MAX(1,Settings!$C$11-Settings!$C$10))) | Q21: =IF(B21="","",IF(N21<=0,"Out of stock",IF(N21<=I21,"Restock","OK"))) | R21: =IF(B21="","",MAX(N21,0)*J21)
J22: =IF(B22="","",E22+F22/60*Settings!$C$8) | K22: =IF(OR(B22="",G22=0),"",(G22-J22)/G22) | L22: =IF(B22="","",SUMIFS(Production!$E$7:$E$204,Production!$C$7:$C$204,B22,Production!$G$7:$G$204,"Done")) | M22: =IF(B22="","",SUMIFS(Sales!$E$7:$E$504,Sales!$C$7:$C$504,B22)) | N22: =IF(B22="","",H22+L22-M22) | O22: =IF(B22="","",SUMIFS(Sales!$E$7:$E$504,Sales!$C$7:$C$504,B22,Sales!$B$7:$B$504,">="&Settings!$C$10,Sales!$B$7:$B$504,"<="&Settings!$C$11)) | P22: =IF(OR(B22="",O22=0),"",MAX(N22,0)/(O22/MAX(1,Settings!$C$11-Settings!$C$10))) | Q22: =IF(B22="","",IF(N22<=0,"Out of stock",IF(N22<=I22,"Restock","OK"))) | R22: =IF(B22="","",MAX(N22,0)*J22)
J23: =IF(B23="","",E23+F23/60*Settings!$C$8) | K23: =IF(OR(B23="",G23=0),"",(G23-J23)/G23) | L23: =IF(B23="","",SUMIFS(Production!$E$7:$E$204,Production!$C$7:$C$204,B23,Production!$G$7:$G$204,"Done")) | M23: =IF(B23="","",SUMIFS(Sales!$E$7:$E$504,Sales!$C$7:$C$504,B23)) | N23: =IF(B23="","",H23+L23-M23) | O23: =IF(B23="","",SUMIFS(Sales!$E$7:$E$504,Sales!$C$7:$C$504,B23,Sales!$B$7:$B$504,">="&Settings!$C$10,Sales!$B$7:$B$504,"<="&Settings!$C$11)) | P23: =IF(OR(B23="",O23=0),"",MAX(N23,0)/(O23/MAX(1,Settings!$C$11-Settings!$C$10))) | Q23: =IF(B23="","",IF(N23<=0,"Out of stock",IF(N23<=I23,"Restock","OK"))) | R23: =IF(B23="","",MAX(N23,0)*J23)
J24: =IF(B24="","",E24+F24/60*Settings!$C$8) | K24: =IF(OR(B24="",G24=0),"",(G24-J24)/G24) | L24: =IF(B24="","",SUMIFS(Production!$E$7:$E$204,Production!$C$7:$C$204,B24,Production!$G$7:$G$204,"Done")) | M24: =IF(B24="","",SUMIFS(Sales!$E$7:$E$504,Sales!$C$7:$C$504,B24)) | N24: =IF(B24="","",H24+L24-M24) | O24: =IF(B24="","",SUMIFS(Sales!$E$7:$E$504,Sales!$C$7:$C$504,B24,Sales!$B$7:$B$504,">="&Settings!$C$10,Sales!$B$7:$B$504,"<="&Settings!$C$11)) | P24: =IF(OR(B24="",O24=0),"",MAX(N24,0)/(O24/MAX(1,Settings!$C$11-Settings!$C$10))) | Q24: =IF(B24="","",IF(N24<=0,"Out of stock",IF(N24<=I24,"Restock","OK"))) | R24: =IF(B24="","",MAX(N24,0)*J24)
... J104: =IF(B104="","",E104+F104/60*Settings!$C$8) | K104: =IF(OR(B104="",G104=0),"",(G104-J104)/G104) | L104: =IF(B104="","",SUMIFS(Production!$E$7:$E$204,Production!$C$7:$C$204,B104,Production!$G$7:$G$204,"Done")) | M104: =IF(B104="","",SUMIFS(Sales!$E$7:$E$504,Sales!$C$7:$C$504,B104)) | N104: =IF(B104="","",H104+L104-M104) | O104: =IF(B104="","",SUMIFS(Sales!$E$7:$E$504,Sales!$C$7:$C$504,B104,Sales!$B$7:$B$504,">="&Settings!$C$10,Sales!$B$7:$B$504,"<="&Settings!$C$11)) | P104: =IF(OR(B104="",O104=0),"",MAX(N104,0)/(O104/MAX(1,Settings!$C$11-Settings!$C$10))) | Q104: =IF(B104="","",IF(N104<=0,"Out of stock",IF(N104<=I104,"Restock","OK"))) | R104: =IF(B104="","",MAX(N104,0)*J104)

Sheet Sales
B2: SALES
B3: Sales
B4: One row per sale. Leave the price empty to use the list price.
B6: Date | C6: SKU | D6: Product | E6: Qty | F6: Channel | G6: Price (if different) | H6: Price used | I6: Revenue
B7: =Settings!$C$9-1 -> 46310 | C7: CND-01 | D7: =IF(C7="","",IFERROR(INDEX(Products!$C$7:$C$104,MATCH(C7,Products!$B$7:$B$104,0)),"Unknown SKU")) -> Fig candle | E7: 2 | F7: Instagram | H7: =IF(C7="","",IF(G7="",IFERROR(INDEX(Products!$G$7:$G$104,MATCH(C7,Products!$B$7:$B$104,0)),0),G7)) -> 38 | I7: =IF(C7="","",E7*H7) -> 76
B8: =Settings!$C$9-3 -> 46308 | C8: PRN-01 | D8: =IF(C8="","",IFERROR(INDEX(Products!$C$7:$C$104,MATCH(C8,Products!$B$7:$B$104,0)),"Unknown SKU")) -> Art print A3 | E8: 3 | F8: Website | H8: =IF(C8="","",IF(G8="",IFERROR(INDEX(Products!$G$7:$G$104,MATCH(C8,Products!$B$7:$B$104,0)),0),G8)) -> 30 | I8: =IF(C8="","",E8*H8) -> 90
B9: =Settings!$C$9-4 -> 46307 | C9: CER-01 | D9: =IF(C9="","",IFERROR(INDEX(Products!$C$7:$C$104,MATCH(C9,Products!$B$7:$B$104,0)),"Unknown SKU")) -> Stoneware mug | E9: 1 | F9: Shop / in person | H9: =IF(C9="","",IF(G9="",IFERROR(INDEX(Products!$G$7:$G$104,MATCH(C9,Products!$B$7:$B$104,0)),0),G9)) -> 55 | I9: =IF(C9="","",E9*H9) -> 55
B10: =Settings!$C$9-6 -> 46305 | C10: CND-02 | D10: =IF(C10="","",IFERROR(INDEX(Products!$C$7:$C$104,MATCH(C10,Products!$B$7:$B$104,0)),"Unknown SKU")) -> Cedar candle | E10: 4 | F10: Wholesale | G10: 30 | H10: =IF(C10="","",IF(G10="",IFERROR(INDEX(Products!$G$7:$G$104,MATCH(C10,Products!$B$7:$B$104,0)),0),G10)) -> 30 | I10: =IF(C10="","",E10*H10) -> 120
B11: =Settings!$C$9-9 -> 46302 | C11: TXT-01 | D11: =IF(C11="","",IFERROR(INDEX(Products!$C$7:$C$104,MATCH(C11,Products!$B$7:$B$104,0)),"Unknown SKU")) -> Linen tote | E11: 2 | F11: Marketplace | H11: =IF(C11="","",IF(G11="",IFERROR(INDEX(Products!$G$7:$G$104,MATCH(C11,Products!$B$7:$B$104,0)),0),G11)) -> 45 | I11: =IF(C11="","",E11*H11) -> 90
B12: =Settings!$C$9-11 -> 46300 | C12: CND-01 | D12: =IF(C12="","",IFERROR(INDEX(Products!$C$7:$C$104,MATCH(C12,Products!$B$7:$B$104,0)),"Unknown SKU")) -> Fig candle | E12: 1 | F12: WhatsApp | H12: =IF(C12="","",IF(G12="",IFERROR(INDEX(Products!$G$7:$G$104,MATCH(C12,Products!$B$7:$B$104,0)),0),G12)) -> 38 | I12: =IF(C12="","",E12*H12) -> 38
B13: =Settings!$C$9-13 -> 46298 | C13: CER-02 | D13: =IF(C13="","",IFERROR(INDEX(Products!$C$7:$C$104,MATCH(C13,Products!$B$7:$B$104,0)),"Unknown SKU")) -> Serving bowl | E13: 1 | F13: Instagram | H13: =IF(C13="","",IF(G13="",IFERROR(INDEX(Products!$G$7:$G$104,MATCH(C13,Products!$B$7:$B$104,0)),0),G13)) -> 95 | I13: =IF(C13="","",E13*H13) -> 95
B14: =Settings!$C$9-16 -> 46295 | C14: PRN-01 | D14: =IF(C14="","",IFERROR(INDEX(Products!$C$7:$C$104,MATCH(C14,Products!$B$7:$B$104,0)),"Unknown SKU")) -> Art print A3 | E14: 2 | F14: Website | H14: =IF(C14="","",IF(G14="",IFERROR(INDEX(Products!$G$7:$G$104,MATCH(C14,Products!$B$7:$B$104,0)),0),G14)) -> 30 | I14: =IF(C14="","",E14*H14) -> 60
B15: =Settings!$C$9-19 -> 46292 | C15: CND-01 | D15: =IF(C15="","",IFERROR(INDEX(Products!$C$7:$C$104,MATCH(C15,Products!$B$7:$B$104,0)),"Unknown SKU")) -> Fig candle | E15: 3 | F15: Shop / in person | H15: =IF(C15="","",IF(G15="",IFERROR(INDEX(Products!$G$7:$G$104,MATCH(C15,Products!$B$7:$B$104,0)),0),G15)) -> 38 | I15: =IF(C15="","",E15*H15) -> 114
B16: =Settings!$C$9-22 -> 46289 | C16: TXT-01 | D16: =IF(C16="","",IFERROR(INDEX(Products!$C$7:$C$104,MATCH(C16,Products!$B$7:$B$104,0)),"Unknown SKU")) -> Linen tote | E16: 1 | F16: Instagram | H16: =IF(C16="","",IF(G16="",IFERROR(INDEX(Products!$G$7:$G$104,MATCH(C16,Products!$B$7:$B$104,0)),0),G16)) -> 45 | I16: =IF(C16="","",E16*H16) -> 45
B17: =Settings!$C$9-25 -> 46286 | C17: CER-01 | D17: =IF(C17="","",IFERROR(INDEX(Products!$C$7:$C$104,MATCH(C17,Products!$B$7:$B$104,0)),"Unknown SKU")) -> Stoneware mug | E17: 2 | F17: Website | H17: =IF(C17="","",IF(G17="",IFERROR(INDEX(Products!$G$7:$G$104,MATCH(C17,Products!$B$7:$B$104,0)),0),G17)) -> 55 | I17: =IF(C17="","",E17*H17) -> 110
B18: =Settings!$C$9-29 -> 46282 | C18: CND-02 | D18: =IF(C18="","",IFERROR(INDEX(Products!$C$7:$C$104,MATCH(C18,Products!$B$7:$B$104,0)),"Unknown SKU")) -> Cedar candle | E18: 2 | F18: Instagram | H18: =IF(C18="","",IF(G18="",IFERROR(INDEX(Products!$G$7:$G$104,MATCH(C18,Products!$B$7:$B$104,0)),0),G18)) -> 38 | I18: =IF(C18="","",E18*H18) -> 76
B19: =Settings!$C$9-33 -> 46278 | C19: PRN-01 | D19: =IF(C19="","",IFERROR(INDEX(Products!$C$7:$C$104,MATCH(C19,Products!$B$7:$B$104,0)),"Unknown SKU")) -> Art print A3 | E19: 4 | F19: Marketplace | H19: =IF(C19="","",IF(G19="",IFERROR(INDEX(Products!$G$7:$G$104,MATCH(C19,Products!$B$7:$B$104,0)),0),G19)) -> 30 | I19: =IF(C19="","",E19*H19) -> 120
B20: =Settings!$C$9-37 -> 46274 | C20: CND-01 | D20: =IF(C20="","",IFERROR(INDEX(Products!$C$7:$C$104,MATCH(C20,Products!$B$7:$B$104,0)),"Unknown SKU")) -> Fig candle | E20: 2 | F20: Website | H20: =IF(C20="","",IF(G20="",IFERROR(INDEX(Products!$G$7:$G$104,MATCH(C20,Products!$B$7:$B$104,0)),0),G20)) -> 38 | I20: =IF(C20="","",E20*H20) -> 76
B21: =Settings!$C$9-41 -> 46270 | C21: TXT-01 | D21: =IF(C21="","",IFERROR(INDEX(Products!$C$7:$C$104,MATCH(C21,Products!$B$7:$B$104,0)),"Unknown SKU")) -> Linen tote | E21: 3 | F21: Shop / in person | H21: =IF(C21="","",IF(G21="",IFERROR(INDEX(Products!$G$7:$G$104,MATCH(C21,Products!$B$7:$B$104,0)),0),G21)) -> 45 | I21: =IF(C21="","",E21*H21) -> 135
B22: =Settings!$C$9-44 -> 46267 | C22: CER-01 | D22: =IF(C22="","",IFERROR(INDEX(Products!$C$7:$C$104,MATCH(C22,Products!$B$7:$B$104,0)),"Unknown SKU")) -> Stoneware mug | E22: 1 | F22: Instagram | H22: =IF(C22="","",IF(G22="",IFERROR(INDEX(Products!$G$7:$G$104,MATCH(C22,Products!$B$7:$B$104,0)),0),G22)) -> 55 | I22: =IF(C22="","",E22*H22) -> 55
B23: =Settings!$C$9-48 -> 46263 | C23: CND-02 | D23: =IF(C23="","",IFERROR(INDEX(Products!$C$7:$C$104,MATCH(C23,Products!$B$7:$B$104,0)),"Unknown SKU")) -> Cedar candle | E23: 3 | F23: Wholesale | G23: 30 | H23: =IF(C23="","",IF(G23="",IFERROR(INDEX(Products!$G$7:$G$104,MATCH(C23,Products!$B$7:$B$104,0)),0),G23)) -> 30 | I23: =IF(C23="","",E23*H23) -> 90
B24: =Settings!$C$9-52 -> 46259 | C24: PRN-01 | D24: =IF(C24="","",IFERROR(INDEX(Products!$C$7:$C$104,MATCH(C24,Products!$B$7:$B$104,0)),"Unknown SKU")) -> Art print A3 | E24: 2 | F24: Website | H24: =IF(C24="","",IF(G24="",IFERROR(INDEX(Products!$G$7:$G$104,MATCH(C24,Products!$B$7:$B$104,0)),0),G24)) -> 30 | I24: =IF(C24="","",E24*H24) -> 60
B25: =Settings!$C$9-55 -> 46256 | C25: CND-01 | D25: =IF(C25="","",IFERROR(INDEX(Products!$C$7:$C$104,MATCH(C25,Products!$B$7:$B$104,0)),"Unknown SKU")) -> Fig candle | E25: 1 | F25: WhatsApp | H25: =IF(C25="","",IF(G25="",IFERROR(INDEX(Products!$G$7:$G$104,MATCH(C25,Products!$B$7:$B$104,0)),0),G25)) -> 38 | I25: =IF(C25="","",E25*H25) -> 38
D26: =IF(C26="","",IFERROR(INDEX(Products!$C$7:$C$104,MATCH(C26,Products!$B$7:$B$104,0)),"Unknown SKU")) | H26: =IF(C26="","",IF(G26="",IFERROR(INDEX(Products!$G$7:$G$104,MATCH(C26,Products!$B$7:$B$104,0)),0),G26)) | I26: =IF(C26="","",E26*H26)
D27: =IF(C27="","",IFERROR(INDEX(Products!$C$7:$C$104,MATCH(C27,Products!$B$7:$B$104,0)),"Unknown SKU")) | H27: =IF(C27="","",IF(G27="",IFERROR(INDEX(Products!$G$7:$G$104,MATCH(C27,Products!$B$7:$B$104,0)),0),G27)) | I27: =IF(C27="","",E27*H27)
D28: =IF(C28="","",IFERROR(INDEX(Products!$C$7:$C$104,MATCH(C28,Products!$B$7:$B$104,0)),"Unknown SKU")) | H28: =IF(C28="","",IF(G28="",IFERROR(INDEX(Products!$G$7:$G$104,MATCH(C28,Products!$B$7:$B$104,0)),0),G28)) | I28: =IF(C28="","",E28*H28)
D29: =IF(C29="","",IFERROR(INDEX(Products!$C$7:$C$104,MATCH(C29,Products!$B$7:$B$104,0)),"Unknown SKU")) | H29: =IF(C29="","",IF(G29="",IFERROR(INDEX(Products!$G$7:$G$104,MATCH(C29,Products!$B$7:$B$104,0)),0),G29)) | I29: =IF(C29="","",E29*H29)
D30: =IF(C30="","",IFERROR(INDEX(Products!$C$7:$C$104,MATCH(C30,Products!$B$7:$B$104,0)),"Unknown SKU")) | H30: =IF(C30="","",IF(G30="",IFERROR(INDEX(Products!$G$7:$G$104,MATCH(C30,Products!$B$7:$B$104,0)),0),G30)) | I30: =IF(C30="","",E30*H30)
D31: =IF(C31="","",IFERROR(INDEX(Products!$C$7:$C$104,MATCH(C31,Products!$B$7:$B$104,0)),"Unknown SKU")) | H31: =IF(C31="","",IF(G31="",IFERROR(INDEX(Products!$G$7:$G$104,MATCH(C31,Products!$B$7:$B$104,0)),0),G31)) | I31: =IF(C31="","",E31*H31)
D32: =IF(C32="","",IFERROR(INDEX(Products!$C$7:$C$104,MATCH(C32,Products!$B$7:$B$104,0)),"Unknown SKU")) | H32: =IF(C32="","",IF(G32="",IFERROR(INDEX(Products!$G$7:$G$104,MATCH(C32,Products!$B$7:$B$104,0)),0),G32)) | I32: =IF(C32="","",E32*H32)
D33: =IF(C33="","",IFERROR(INDEX(Products!$C$7:$C$104,MATCH(C33,Products!$B$7:$B$104,0)),"Unknown SKU")) | H33: =IF(C33="","",IF(G33="",IFERROR(INDEX(Products!$G$7:$G$104,MATCH(C33,Products!$B$7:$B$104,0)),0),G33)) | I33: =IF(C33="","",E33*H33)
D34: =IF(C34="","",IFERROR(INDEX(Products!$C$7:$C$104,MATCH(C34,Products!$B$7:$B$104,0)),"Unknown SKU")) | H34: =IF(C34="","",IF(G34="",IFERROR(INDEX(Products!$G$7:$G$104,MATCH(C34,Products!$B$7:$B$104,0)),0),G34)) | I34: =IF(C34="","",E34*H34)
D35: =IF(C35="","",IFERROR(INDEX(Products!$C$7:$C$104,MATCH(C35,Products!$B$7:$B$104,0)),"Unknown SKU")) | H35: =IF(C35="","",IF(G35="",IFERROR(INDEX(Products!$G$7:$G$104,MATCH(C35,Products!$B$7:$B$104,0)),0),G35)) | I35: =IF(C35="","",E35*H35)
D36: =IF(C36="","",IFERROR(INDEX(Products!$C$7:$C$104,MATCH(C36,Products!$B$7:$B$104,0)),"Unknown SKU")) | H36: =IF(C36="","",IF(G36="",IFERROR(INDEX(Products!$G$7:$G$104,MATCH(C36,Products!$B$7:$B$104,0)),0),G36)) | I36: =IF(C36="","",E36*H36)
D37: =IF(C37="","",IFERROR(INDEX(Products!$C$7:$C$104,MATCH(C37,Products!$B$7:$B$104,0)),"Unknown SKU")) | H37: =IF(C37="","",IF(G37="",IFERROR(INDEX(Products!$G$7:$G$104,MATCH(C37,Products!$B$7:$B$104,0)),0),G37)) | I37: =IF(C37="","",E37*H37)
... D504: =IF(C504="","",IFERROR(INDEX(Products!$C$7:$C$104,MATCH(C504,Products!$B$7:$B$104,0)),"Unknown SKU")) | H504: =IF(C504="","",IF(G504="",IFERROR(INDEX(Products!$G$7:$G$104,MATCH(C504,Products!$B$7:$B$104,0)),0),G504)) | I504: =IF(C504="","",E504*H504)

Sheet Production
B2: WORK IN PROGRESS
B3: Production
B4: Batches and custom orders. At "Done", units go into stock.
B6: Job | C6: SKU | D6: Product | E6: Qty | F6: For (client or stock) | G6: Step | H6: Start | I6: Due | J6: Days left | K6: Status
B7: J-01 | C7: CND-01 | D7: =IF(C7="","",IFERROR(INDEX(Products!$C$7:$C$104,MATCH(C7,Products!$B$7:$B$104,0)),"Unknown SKU")) -> Fig candle | E7: 12 | F7: Stock | G7: Done | H7: =Settings!$C$9-25 -> 46286 | I7: =Settings!$C$9-18 -> 46293 | J7: =IF(OR(C7="",I7="",G7="Done"),"",I7-Settings!$C$9) | K7: =IF(C7="","",IF(G7="Done","Done",IF(I7="","No due date",IF(I7<Settings!$C$9,"Late",IF(I7-Settings!$C$9<=Settings!$C$12,"Due soon","On track"))))) -> Done
B8: J-02 | C8: PRN-01 | D8: =IF(C8="","",IFERROR(INDEX(Products!$C$7:$C$104,MATCH(C8,Products!$B$7:$B$104,0)),"Unknown SKU")) -> Art print A3 | E8: 20 | F8: Stock | G8: Done | H8: =Settings!$C$9-20 -> 46291 | I8: =Settings!$C$9-15 -> 46296 | J8: =IF(OR(C8="",I8="",G8="Done"),"",I8-Settings!$C$9) | K8: =IF(C8="","",IF(G8="Done","Done",IF(I8="","No due date",IF(I8<Settings!$C$9,"Late",IF(I8-Settings!$C$9<=Settings!$C$12,"Due soon","On track"))))) -> Done
B9: J-03 | C9: CER-02 | D9: =IF(C9="","",IFERROR(INDEX(Products!$C$7:$C$104,MATCH(C9,Products!$B$7:$B$104,0)),"Unknown SKU")) -> Serving bowl | E9: 2 | F9: Client: custom set | G9: Finishing | H9: =Settings!$C$9-8 -> 46303 | I9: =Settings!$C$9+2 -> 46313 | J9: =IF(OR(C9="",I9="",G9="Done"),"",I9-Settings!$C$9) -> 2 | K9: =IF(C9="","",IF(G9="Done","Done",IF(I9="","No due date",IF(I9<Settings!$C$9,"Late",IF(I9-Settings!$C$9<=Settings!$C$12,"Due soon","On track"))))) -> Due soon
B10: J-04 | C10: CND-02 | D10: =IF(C10="","",IFERROR(INDEX(Products!$C$7:$C$104,MATCH(C10,Products!$B$7:$B$104,0)),"Unknown SKU")) -> Cedar candle | E10: 10 | F10: Stock | G10: Making | H10: =Settings!$C$9-2 -> 46309 | I10: =Settings!$C$9+6 -> 46317 | J10: =IF(OR(C10="",I10="",G10="Done"),"",I10-Settings!$C$9) -> 6 | K10: =IF(C10="","",IF(G10="Done","Done",IF(I10="","No due date",IF(I10<Settings!$C$9,"Late",IF(I10-Settings!$C$9<=Settings!$C$12,"Due soon","On track"))))) -> On track
B11: J-05 | C11: TXT-01 | D11: =IF(C11="","",IFERROR(INDEX(Products!$C$7:$C$104,MATCH(C11,Products!$B$7:$B$104,0)),"Unknown SKU")) -> Linen tote | E11: 8 | F11: Wholesale order | G11: Quality check | H11: =Settings!$C$9-12 -> 46299 | I11: =Settings!$C$9-1 -> 46310 | J11: =IF(OR(C11="",I11="",G11="Done"),"",I11-Settings!$C$9) -> -1 | K11: =IF(C11="","",IF(G11="Done","Done",IF(I11="","No due date",IF(I11<Settings!$C$9,"Late",IF(I11-Settings!$C$9<=Settings!$C$12,"Due soon","On track"))))) -> Late
D12: =IF(C12="","",IFERROR(INDEX(Products!$C$7:$C$104,MATCH(C12,Products!$B$7:$B$104,0)),"Unknown SKU")) | J12: =IF(OR(C12="",I12="",G12="Done"),"",I12-Settings!$C$9) | K12: =IF(C12="","",IF(G12="Done","Done",IF(I12="","No due date",IF(I12<Settings!$C$9,"Late",IF(I12-Settings!$C$9<=Settings!$C$12,"Due soon","On track")))))
D13: =IF(C13="","",IFERROR(INDEX(Products!$C$7:$C$104,MATCH(C13,Products!$B$7:$B$104,0)),"Unknown SKU")) | J13: =IF(OR(C13="",I13="",G13="Done"),"",I13-Settings!$C$9) | K13: =IF(C13="","",IF(G13="Done","Done",IF(I13="","No due date",IF(I13<Settings!$C$9,"Late",IF(I13-Settings!$C$9<=Settings!$C$12,"Due soon","On track")))))
D14: =IF(C14="","",IFERROR(INDEX(Products!$C$7:$C$104,MATCH(C14,Products!$B$7:$B$104,0)),"Unknown SKU")) | J14: =IF(OR(C14="",I14="",G14="Done"),"",I14-Settings!$C$9) | K14: =IF(C14="","",IF(G14="Done","Done",IF(I14="","No due date",IF(I14<Settings!$C$9,"Late",IF(I14-Settings!$C$9<=Settings!$C$12,"Due soon","On track")))))
D15: =IF(C15="","",IFERROR(INDEX(Products!$C$7:$C$104,MATCH(C15,Products!$B$7:$B$104,0)),"Unknown SKU")) | J15: =IF(OR(C15="",I15="",G15="Done"),"",I15-Settings!$C$9) | K15: =IF(C15="","",IF(G15="Done","Done",IF(I15="","No due date",IF(I15<Settings!$C$9,"Late",IF(I15-Settings!$C$9<=Settings!$C$12,"Due soon","On track")))))
D16: =IF(C16="","",IFERROR(INDEX(Products!$C$7:$C$104,MATCH(C16,Products!$B$7:$B$104,0)),"Unknown SKU")) | J16: =IF(OR(C16="",I16="",G16="Done"),"",I16-Settings!$C$9) | K16: =IF(C16="","",IF(G16="Done","Done",IF(I16="","No due date",IF(I16<Settings!$C$9,"Late",IF(I16-Settings!$C$9<=Settings!$C$12,"Due soon","On track")))))
D17: =IF(C17="","",IFERROR(INDEX(Products!$C$7:$C$104,MATCH(C17,Products!$B$7:$B$104,0)),"Unknown SKU")) | J17: =IF(OR(C17="",I17="",G17="Done"),"",I17-Settings!$C$9) | K17: =IF(C17="","",IF(G17="Done","Done",IF(I17="","No due date",IF(I17<Settings!$C$9,"Late",IF(I17-Settings!$C$9<=Settings!$C$12,"Due soon","On track")))))
D18: =IF(C18="","",IFERROR(INDEX(Products!$C$7:$C$104,MATCH(C18,Products!$B$7:$B$104,0)),"Unknown SKU")) | J18: =IF(OR(C18="",I18="",G18="Done"),"",I18-Settings!$C$9) | K18: =IF(C18="","",IF(G18="Done","Done",IF(I18="","No due date",IF(I18<Settings!$C$9,"Late",IF(I18-Settings!$C$9<=Settings!$C$12,"Due soon","On track")))))
D19: =IF(C19="","",IFERROR(INDEX(Products!$C$7:$C$104,MATCH(C19,Products!$B$7:$B$104,0)),"Unknown SKU")) | J19: =IF(OR(C19="",I19="",G19="Done"),"",I19-Settings!$C$9) | K19: =IF(C19="","",IF(G19="Done","Done",IF(I19="","No due date",IF(I19<Settings!$C$9,"Late",IF(I19-Settings!$C$9<=Settings!$C$12,"Due soon","On track")))))
D20: =IF(C20="","",IFERROR(INDEX(Products!$C$7:$C$104,MATCH(C20,Products!$B$7:$B$104,0)),"Unknown SKU")) | J20: =IF(OR(C20="",I20="",G20="Done"),"",I20-Settings!$C$9) | K20: =IF(C20="","",IF(G20="Done","Done",IF(I20="","No due date",IF(I20<Settings!$C$9,"Late",IF(I20-Settings!$C$9<=Settings!$C$12,"Due soon","On track")))))
D21: =IF(C21="","",IFERROR(INDEX(Products!$C$7:$C$104,MATCH(C21,Products!$B$7:$B$104,0)),"Unknown SKU")) | J21: =IF(OR(C21="",I21="",G21="Done"),"",I21-Settings!$C$9) | K21: =IF(C21="","",IF(G21="Done","Done",IF(I21="","No due date",IF(I21<Settings!$C$9,"Late",IF(I21-Settings!$C$9<=Settings!$C$12,"Due soon","On track")))))
D22: =IF(C22="","",IFERROR(INDEX(Products!$C$7:$C$104,MATCH(C22,Products!$B$7:$B$104,0)),"Unknown SKU")) | J22: =IF(OR(C22="",I22="",G22="Done"),"",I22-Settings!$C$9) | K22: =IF(C22="","",IF(G22="Done","Done",IF(I22="","No due date",IF(I22<Settings!$C$9,"Late",IF(I22-Settings!$C$9<=Settings!$C$12,"Due soon","On track")))))
D23: =IF(C23="","",IFERROR(INDEX(Products!$C$7:$C$104,MATCH(C23,Products!$B$7:$B$104,0)),"Unknown SKU")) | J23: =IF(OR(C23="",I23="",G23="Done"),"",I23-Settings!$C$9) | K23: =IF(C23="","",IF(G23="Done","Done",IF(I23="","No due date",IF(I23<Settings!$C$9,"Late",IF(I23-Settings!$C$9<=Settings!$C$12,"Due soon","On track")))))
... D204: =IF(C204="","",IFERROR(INDEX(Products!$C$7:$C$104,MATCH(C204,Products!$B$7:$B$104,0)),"Unknown SKU")) | J204: =IF(OR(C204="",I204="",G204="Done"),"",I204-Settings!$C$9) | K204: =IF(C204="","",IF(G204="Done","Done",IF(I204="","No due date",IF(I204<Settings!$C$9,"Late",IF(I204-Settings!$C$9<=Settings!$C$12,"Due soon","On track")))))
